{
  "$schema": "https://ui.shadcn.com/schema/registry.json",
  "name": "better-upload",
  "homepage": "https://better-upload.com",
  "syncedAt": "2026-01-18T00:03:53.749Z",
  "itemCount": 4,
  "items": [
    {
      "name": "upload-dropzone-progress",
      "type": "registry:ui",
      "title": "Upload Dropzone with Progress",
      "dependencies": [
        "@better-upload/client",
        "lucide-react",
        "react-dropzone"
      ],
      "registryDependencies": [
        "progress"
      ]
    },
    {
      "name": "upload-dropzone",
      "type": "registry:ui",
      "title": "Upload Dropzone",
      "dependencies": [
        "@better-upload/client",
        "lucide-react",
        "react-dropzone"
      ],
      "registryDependencies": []
    },
    {
      "name": "paste-upload-area",
      "type": "registry:ui",
      "title": "Paste Upload Area",
      "dependencies": [
        "@better-upload/client"
      ],
      "registryDependencies": []
    },
    {
      "name": "upload-button",
      "type": "registry:ui",
      "title": "Upload Button",
      "dependencies": [
        "@better-upload/client",
        "lucide-react"
      ],
      "registryDependencies": [
        "button"
      ]
    }
  ]
}